hf_instella/__init__.py
hf_instella/configuration_instella.py
hf_instella/convert_instella_to_hf.py
hf_instella/modeling_instella.py
instella/__init__.py
instella/aliases.py
instella/beam_search.py
instella/checkpoint.py
instella/config.py
instella/exceptions.py
instella/initialization.py
instella/model.py
instella/optim.py
instella/py.typed
instella/safetensors_util.py
instella/tokenizer.py
instella/torch_util.py
instella/train.py
instella/util.py
instella/version.py
instella/data/__init__.py
instella/data/collator.py
instella/data/iterable_dataset.py
instella/data/memmap_dataset.py
instella/data/util.py
instella/eval/__init__.py
instella/eval/downstream.py
instella/eval/evaluator.py
instella_internal_test-0.1.0.dist-info/licenses/LICENSE
instella_internal_test-0.1.0.dist-info/licenses/NOTICES
instella_internal_test-0.1.0.dist-info/METADATA
instella_internal_test-0.1.0.dist-info/WHEEL
instella_internal_test-0.1.0.dist-info/top_level.txt
instella_internal_test-0.1.0.dist-info/RECORD
