Metadata-Version: 2.4
Name: instella-internal-test
Version: 0.1.0
Summary: Open language model trained by AMD GenAI team.this is a fork version for test only
Author: AMD GenAI Team
License: Instella-3B [RESEARCH-ONLY RAIL-MS]
Project-URL: Homepage, https://github.com/AMD-AIG-AIMA/Instella
Project-URL: Repository, https://github.com/AMD-AIG-AIMA/Instella
Requires-Python: >=3.8
License-File: LICENSE
License-File: NOTICES
Requires-Dist: numpy
Requires-Dist: omegaconf
Requires-Dist: rich
Requires-Dist: boto3
Requires-Dist: google-cloud-storage
Requires-Dist: tokenizers
Requires-Dist: packaging
Requires-Dist: cached_path>=1.6.2
Requires-Dist: transformers
Provides-Extra: dev
Requires-Dist: ruff; extra == "dev"
Requires-Dist: mypy<1.4,>=1.0; extra == "dev"
Requires-Dist: black<24.0,>=23.1; extra == "dev"
Requires-Dist: isort<5.13,>=5.12; extra == "dev"
Requires-Dist: pytest; extra == "dev"
Requires-Dist: pytest-sphinx; extra == "dev"
Requires-Dist: twine>=1.11.0; extra == "dev"
Requires-Dist: setuptools; extra == "dev"
Requires-Dist: wheel; extra == "dev"
Requires-Dist: build; extra == "dev"
Provides-Extra: train
Requires-Dist: wandb; extra == "train"
Requires-Dist: click; extra == "train"
Requires-Dist: torchmetrics; extra == "train"
Requires-Dist: smashed[remote]>=0.21.1; extra == "train"
Requires-Dist: safetensors; extra == "train"
Requires-Dist: datasets; extra == "train"
Requires-Dist: scikit-learn; extra == "train"
Requires-Dist: msgspec>=0.14.0; extra == "train"
Provides-Extra: all
Requires-Dist: instella[dev,train]; extra == "all"
Dynamic: license-file
